huaweicloudsdkcloudtest/__init__.py
huaweicloudsdkcloudtest/v1/__init__.py
huaweicloudsdkcloudtest/v1/cloudtest_async_client.py
huaweicloudsdkcloudtest/v1/cloudtest_client.py
huaweicloudsdkcloudtest/v1/model/__init__.py
huaweicloudsdkcloudtest/v1/model/add_case_result_four_request.py
huaweicloudsdkcloudtest/v1/model/add_case_result_four_response.py
huaweicloudsdkcloudtest/v1/model/add_feature_request.py
huaweicloudsdkcloudtest/v1/model/add_feature_response.py
huaweicloudsdkcloudtest/v1/model/add_relations_info.py
huaweicloudsdkcloudtest/v1/model/add_resource_info.py
huaweicloudsdkcloudtest/v1/model/add_test_case_comment_request.py
huaweicloudsdkcloudtest/v1/model/add_test_case_comment_response.py
huaweicloudsdkcloudtest/v1/model/add_test_case_result_info.py
huaweicloudsdkcloudtest/v1/model/add_test_case_result_log_info.py
huaweicloudsdkcloudtest/v1/model/add_test_case_result_log_request.py
huaweicloudsdkcloudtest/v1/model/add_test_case_result_log_response.py
huaweicloudsdkcloudtest/v1/model/add_test_item_info.py
huaweicloudsdkcloudtest/v1/model/alarm_statistics_query.py
huaweicloudsdkcloudtest/v1/model/alarm_template_info.py
huaweicloudsdkcloudtest/v1/model/alert_group.py
huaweicloudsdkcloudtest/v1/model/alert_level.py
huaweicloudsdkcloudtest/v1/model/alert_statistics_dto.py
huaweicloudsdkcloudtest/v1/model/alert_template_vo.py
huaweicloudsdkcloudtest/v1/model/api_error.py
huaweicloudsdkcloudtest/v1/model/array_node.py
huaweicloudsdkcloudtest/v1/model/asset.py
huaweicloudsdkcloudtest/v1/model/asset_export_param.py
huaweicloudsdkcloudtest/v1/model/asset_tree.py
huaweicloudsdkcloudtest/v1/model/assigned_user_info.py
huaweicloudsdkcloudtest/v1/model/associate_defect_info_vo.py
huaweicloudsdkcloudtest/v1/model/associate_issue_info_vo.py
huaweicloudsdkcloudtest/v1/model/attachment_file_vo.py
huaweicloudsdkcloudtest/v1/model/attachment_info.py
huaweicloudsdkcloudtest/v1/model/attachment_vo.py
huaweicloudsdkcloudtest/v1/model/attribute_change.py
huaweicloudsdkcloudtest-3.1.184.dist-info/METADATA
huaweicloudsdkcloudtest-3.1.184.dist-info/WHEEL
huaweicloudsdkcloudtest-3.1.184.dist-info/licenses/LICENSE
huaweicloudsdkcloudtest-3.1.184.dist-info/RECORD
